forest_utils/__init__.py
forest_utils/cli.py
forest_utils/datasets.py
forest_utils/export_keras.py
forest_utils/export_spacy.py
forest_utils/export_transformers.py
forest_utils/utils/__init__.py
forest_utils/utils/create.py
forest_utils/utils/pull.py
forest_utils-1.0.2.dist-info/METADATA
forest_utils-1.0.2.dist-info/WHEEL
forest_utils-1.0.2.dist-info/entry_points.txt
forest_utils-1.0.2.dist-info/top_level.txt
forest_utils-1.0.2.dist-info/RECORD
