Metadata-Version: 2.1
Name: forest-utils
Version: 1.0.2
Summary: Package for Smoketrees model zoo
Home-page: https://github.com/smoke-trees/forest-utils
Author: Smoketrees
Author-email: info@smoketrees.dev
Maintainer: Ubaid Usmani
Maintainer-email: usmaniubaid@gmail.com
License: UNKNOWN
Project-URL: Documentation, https://github.com/smoke-trees/forest-utils
Project-URL: Code, https://github.com/smoke-trees/forest-utils
Project-URL: Issue tracker, https://github.com/smoke-trees/forest-utils/issues
Platform: UNKNOWN
Classifier: Development Status :: 5 - Production/Stable
Classifier: Intended Audience :: Developers
Classifier: License :: OSI Approved :: GNU General Public License (GPL)
Classifier: Operating System :: OS Independent
Classifier: Programming Language :: Python :: 3
Classifier: Programming Language :: Python :: 3 :: Only
Classifier: Programming Language :: Python :: 3.6
Classifier: Topic :: Scientific/Engineering :: Artificial Intelligence
Classifier: Topic :: Scientific/Engineering :: Image Recognition
Requires-Python: >=3.6
Requires-Dist: gdown (==3.11.1)
Requires-Dist: requests (==2.24.0)
Requires-Dist: tensorflow (==2.3.0)
Requires-Dist: spacy (==2.2.0)
Requires-Dist: pandas
Requires-Dist: click
Requires-Dist: transformers
